boyer_moore_algorithmus/__init__.py
boyer_moore_algorithmus/boyer.py
boyer_moore_algorithmus-1.0.3.dist-info/METADATA
boyer_moore_algorithmus-1.0.3.dist-info/WHEEL
boyer_moore_algorithmus-1.0.3.dist-info/top_level.txt
boyer_moore_algorithmus-1.0.3.dist-info/RECORD
