Metadata-Version: 2.2
Name: boyer_moore_algorithmus
Version: 1.0.3
Dynamic: description
Dynamic: description-content-type
